MANIFEST.in
README.md
setup.py
jsonhyperschema_codec/__init__.py
jsonhyperschema_codec/utils.py
jsonhyperschema_codec.egg-info/PKG-INFO
jsonhyperschema_codec.egg-info/SOURCES.txt
jsonhyperschema_codec.egg-info/dependency_links.txt
jsonhyperschema_codec.egg-info/entry_points.txt
jsonhyperschema_codec.egg-info/requires.txt
jsonhyperschema_codec.egg-info/top_level.txt