Metadata-Version: 1.1
Name: jsonhyperschema-codec
Version: 1.0.3
Summary: A JSON Hyper-Schema codec for Core API.
Home-page: http://github.com/core-api/python-jsonhyperschema-codec/
Author: Tom Christie
Author-email: tom@tomchristie.com
License: BSD
Platform: UNKNOWN
Classifier: Intended Audience :: Developers
Classifier: License :: OSI Approved :: BSD License
Classifier: Operating System :: OS Independent
Classifier: Programming Language :: Python
Classifier: Programming Language :: Python :: 3
